AUTHORS
ChangeLog
MANIFEST.in
README.rst
requirements.txt
setup.cfg
setup.py
leonardo_news.egg-info/PKG-INFO
leonardo_news.egg-info/SOURCES.txt
leonardo_news.egg-info/dependency_links.txt
leonardo_news.egg-info/not-zip-safe
leonardo_news.egg-info/pbr.json
leonardo_news.egg-info/requires.txt
leonardo_news.egg-info/top_level.txt
news/__init__.py
news/models.py
news/overrides.py
news/views.py
news/apps/__init__.py
news/apps/news.py
news/category/__init__.py
news/category/extensions/__init__.py
news/category/extensions/category.py
news/locale/cs/LC_MESSAGES/django.po
news/locale/en/LC_MESSAGES/django.po
news/locale/ru/LC_MESSAGES/django.po
news/migrations/__init__.py
news/templates/articles/article_detail.html
news/templates/articles/article_list.html
news/templates/articles/base.html
news/templates/widget/news/_item.html
news/templates/widget/news/default.html
news/widget/__init__.py
news/widget/news/__init__.py
news/widget/news/models.py
requirements/default.txt
requirements/extras/taggit.txt